flask_manageio/__init__.py
flask_manageio/cli.py
flask_manageio/project_bed/__init__.py
flask_manageio/project_bed/apidoc.py
flask_manageio/project_bed/app.py
flask_manageio/project_bed/config.py
flask_manageio/project_bed/db.py
flask_manageio/project_bed/ma.py
flask_manageio/project_bed/controller/__init__.py
flask_manageio/project_bed/controller/home.py
flask_manageio/project_bed/helpers/__init__.py
flask_manageio/project_bed/helpers/api_doc.py
flask_manageio/project_bed/model/__init__.py
flask_manageio/project_bed/model/DTO/__init__.py
flask_manageio/project_bed/model/DTO/base_schema.py
flask_manageio/project_bed/model/Entity/__init__.py
flask_manageio/project_bed/model/Entity/base_entity.py
flask_manageio/project_bed/service/__init__.py
flask_manageio/project_bed/service/home_service.py
flask_manageio-0.1.0.dist-info/METADATA
flask_manageio-0.1.0.dist-info/WHEEL
flask_manageio-0.1.0.dist-info/entry_points.txt
flask_manageio-0.1.0.dist-info/top_level.txt
flask_manageio-0.1.0.dist-info/RECORD
