Metadata-Version: 2.1
Name: flask-manageio
Version: 0.1.0
Summary: My first Python library
Author: Dardan Iseni
License: MIT
Requires-Dist: Flask (==2.1.3)
Requires-Dist: Flask-Migrate (==3.1.0)
Requires-Dist: Flask-SQLAlchemy (==2.5.1)
Requires-Dist: Flask-marshmallow (==0.14.0)
Requires-Dist: Flask-JWT-Extended (==4.4.2)
Requires-Dist: Flask-RESTful (==0.3.9)
